satnogs_webscraper/__init__.py
satnogs_webscraper/constants.py
satnogs_webscraper/image_utils.py
satnogs_webscraper/mainCLI.py
satnogs_webscraper/observation_dataset.py
satnogs_webscraper/observation_list_scraper.py
satnogs_webscraper/observation_scraper.py
satnogs_webscraper/progress_utils.py
satnogs_webscraper/request_utils.py
satnogs_webscraper/scraper.py
satnogs_webscraper-1.4.4.dist-info/LICENSE.rst
satnogs_webscraper-1.4.4.dist-info/METADATA
satnogs_webscraper-1.4.4.dist-info/WHEEL
satnogs_webscraper-1.4.4.dist-info/top_level.txt
satnogs_webscraper-1.4.4.dist-info/RECORD
